{"currentLocation":3,"currentScene":0,"difficulty":3,"playerInventory":[{"amount":1,"equipped":false,"id":1,"rarity":0,"type":1}],"population":[{"alive":true,"character":1},{"alive":true,"character":0},{"alive":true,"character":2},{"alive":true,"character":3},{"alive":true,"character":4},{"alive":true,"character":5},{"alive":true,"character":6},{"alive":true,"character":7},{"alive":true,"character":8},{"alive":true,"character":9},{"alive":true,"character":10},{"alive":true,"character":11},{"alive":true,"character":12},{"alive":true,"character":13},{"alive":true,"character":14},{"alive":true,"character":15},{"alive":true,"character":16},{"alive":true,"character":17},{"alive":true,"character":18},{"alive":true,"character":19},{"alive":true,"character":20},{"alive":true,"character":21},{"alive":true,"character":22},{"alive":true,"character":23},{"alive":true,"character":24},{"alive":true,"character":25},{"alive":true,"character":26}]}